pyproximase/__init__.py
pyproximase/version.py
pyproximase/core/__init__.py
pyproximase/core/client.py
pyproximase/core/de_client.py
pyproximase/core/de_handlers.py
pyproximase/core/de_types.py
pyproximase/core/handlers.py
pyproximase/core/types.py
pyproximase/proto/__init__.py
pyproximase/proto/admin_pb2.py
pyproximase/proto/admin_pb2_grpc.py
pyproximase/proto/common_pb2.py
pyproximase/proto/common_pb2_grpc.py
pyproximase/proto/config_pb2.py
pyproximase/proto/config_pb2_grpc.py
pyproximase/proto/frontend_pb2.py
pyproximase/proto/frontend_pb2_grpc.py
pyproximase/proto/proxima_se_pb2.py
pyproximase/proto/proxima_se_pb2_grpc.py
pyproximase/proto/repository_de_pb2.py
pyproximase/proto/repository_de_pb2_grpc.py
pyproximase-0.7.0.dist-info/METADATA
pyproximase-0.7.0.dist-info/WHEEL
pyproximase-0.7.0.dist-info/top_level.txt
pyproximase-0.7.0.dist-info/RECORD
